pypackproxy/__init__.py
pypackproxy/__main__.py
pypackproxy/configuration.py
pypackproxy/packs.py
pypackproxy/renderer.py
pypackproxy/root.py
pypackproxy/simple.py
pypackproxy/utils.py
pypackproxy/data/__init__.py
pypackproxy/data/config_spec.ini
pypackproxy/data/favicon.ico
pypackproxy/templates/admin.html
pypackproxy/templates/base.html
pypackproxy/templates/index.html
pypackproxy/templates/login.html
pypackproxy/templates/overview.html
pypackproxy/templates/project.html
pypackproxy-0.3.1.dist-info/LICENSE.txt
pypackproxy-0.3.1.dist-info/METADATA
pypackproxy-0.3.1.dist-info/WHEEL
pypackproxy-0.3.1.dist-info/entry_points.txt
pypackproxy-0.3.1.dist-info/top_level.txt
pypackproxy-0.3.1.dist-info/RECORD
